MANIFEST.in
README
distribute_setup.py
setup.py
virtualenvwrapper/__init__.py
virtualenvwrapper/alex.py
virtualenvwrapper.alex.egg-info/PKG-INFO
virtualenvwrapper.alex.egg-info/SOURCES.txt
virtualenvwrapper.alex.egg-info/dependency_links.txt
virtualenvwrapper.alex.egg-info/entry_points.txt
virtualenvwrapper.alex.egg-info/namespace_packages.txt
virtualenvwrapper.alex.egg-info/not-zip-safe
virtualenvwrapper.alex.egg-info/top_level.txt