Metadata-Version: 1.1
Name: virtualenvwrapper.alex
Version: 0.1
Summary: virtualenvwrapper plugin to alias common typos
Home-page: https://bitbucket.org/dhellmann/virtualenvwrapper.alex
Author: Doug Hellmann
Author-email: doug.hellmann@gmail.com
License: UNKNOWN
Platform: Any
Classifier: Development Status :: 3 - Alpha
Classifier: License :: OSI Approved :: BSD License
Classifier: Programming Language :: Python
Classifier: Programming Language :: Python :: 2
Classifier: Intended Audience :: Developers
Classifier: Environment :: Console
Classifier: Framework :: Django
Requires: virtualenv
Requires: virtualenvwrapper (>=2.9)
Provides: virtualenvwrapper.django
